worldgeo/__init__.py
worldgeo/builder.py
worldgeo/collect.py
worldgeo/index.py
worldgeo/misc.py
worldgeo/sharded.py
worldgeo-1.3.2.dist-info/METADATA
worldgeo-1.3.2.dist-info/WHEEL
worldgeo-1.3.2.dist-info/entry_points.txt
worldgeo-1.3.2.dist-info/top_level.txt
worldgeo-1.3.2.dist-info/RECORD
