Metadata-Version: 2.1
Name: worldgeo
Version: 1.3.2
Summary: world geohash index
Author-email: Pavel Vorobyev <aquavitale@yandex.ru>
License: MIT
Project-URL: Source, https://github.com/viert/worldgeo
Keywords: geohash,world,index,geoindex
Requires-Python: >=3.11
Requires-Dist: python-geohash
Requires-Dist: requests
Requires-Dist: shapely
